{
  "publications": [
    {
      "id": "SNQR-2025-050",
      "title": "GST and the Price Puzzle: Consumer Behavior, Industry Strategies, and Policy Lessons from India and Abroad",
      "deck": "This research investigates how changes in India’s Goods and Services Tax (GST) reshape consumer behavior, industry pricing strategies, and supply chain dynamics across major sectors. By comparing theory with real-world outcomes—and drawing lessons from international GST/VAT regimes—it highlights unintended distortions, behavioral shifts, and policy pathways to align tax design with affordability, competitiveness, and growth.",
      "division": "Engines of State Research",
      "format": "Research",
      "cat": "flagship",
      "publishDate": "2025-10-06",
      "editorsPick": true,
      "keywords": [
        "Goods and Services Tax (GST)",
        "Indirect taxation",
        "Consumer psychology",
        "Price pass-through",
        "Inverted duty structure",
        "Input tax credit (ITC)",
        "Supply chain distortion",
        "FMCG sector taxation",
        "Automobile demand elasticity",
        "Healthcare affordability",
        "Real estate pricing",
        "Policy rationalization"
      ],
      "jelCodes": [
        "H22",
        "H25",
        "H32",
        "H71",
        "E31",
        "D12",
        "L11",
        "L52",
        "F13",
        "Q18",
        "I18",
        "O24"
      ],
      "pages": 24,
      "copyright": " 2025 Saptanga Nupura Quant Research",
      "keyTakeaways": [
        "Psychological Lens on Taxation: GST changes affect not only prices but also consumer trust, timing of purchases, and perception of affordability across essential vs discretionary goods.",
        "Industry Adaptation Matters: Firms adjust via packaging, sourcing, pricing, and marketing strategies, often diluting or amplifying the intended consumer benefits of GST reforms.",
        "Supply Chain Paradoxes: Exemptions and inverted duty structures can create cost burdens that paradoxically raise prices for “tax-free” goods, undermining GST’s efficiency.",
        "Sector-Specific Divergence: While sectors like FMCG or textiles may pass GST cuts to consumers, industries like real estate and automobiles exhibit partial or distorted transmission, creating gaps between theory and practice.",
        "Policy & Global Lessons: International GST/VAT experiences show that simplification (fewer slabs, zero-rating essentials) reduces distortions. India can adapt these lessons to refine its GST, ensuring better alignment of policy intent with ground reality."
      ],
      "image": "/assets/cover/SNQR-2025-050.png",
      "summary": {
        "pdf": "/assets/research/SNQR-2025-050/summary/index.pdf",
        "pptx": "/assets/research/SNQR-2025-050/summary/index.pptx"
      },
      "reader": { "type": "pdf", "src": "/assets/research/SNQR-2025-050/pdf/index.pdf" },
      "audio": { "src": "/assets/research/SNQR-2025-050/audio/index.mp3" },
      "url": "/research/paper.html?id=SNQR-2025-050",
      "hasArticles": true,
      "articlesCount": 36,
      "articleIds": [
        "SNQR-2025-050-A01","SNQR-2025-050-A02","SNQR-2025-050-A03","SNQR-2025-050-A04","SNQR-2025-050-A05","SNQR-2025-050-A06",
        "SNQR-2025-050-A07","SNQR-2025-050-A08","SNQR-2025-050-A09","SNQR-2025-050-A10","SNQR-2025-050-A11","SNQR-2025-050-A12",
        "SNQR-2025-050-A13","SNQR-2025-050-A14","SNQR-2025-050-A15","SNQR-2025-050-A16","SNQR-2025-050-A17","SNQR-2025-050-A18",
        "SNQR-2025-050-A19","SNQR-2025-050-A20","SNQR-2025-050-A21","SNQR-2025-050-A22","SNQR-2025-050-A23","SNQR-2025-050-A24",
        "SNQR-2025-050-A25","SNQR-2025-050-A26","SNQR-2025-050-A27","SNQR-2025-050-A28","SNQR-2025-050-A29","SNQR-2025-050-A30",
        "SNQR-2025-050-A31","SNQR-2025-050-A32","SNQR-2025-050-A33","SNQR-2025-050-A34","SNQR-2025-050-A35","SNQR-2025-050-A36"
      ]
    },
    {
      "id": "SNQR-2025-001",
      "title": "When Real Rates Blink: Gold’s Ascent, Dollar Gravity, and the September Tape",
      "deck": "",
      "division": "Arc of Markets Research",
      "format": "Research",
      "cat": "flagship",
      "publishDate": "2025-07-29",
      "editorsPick": true,
      "keywords": ["real rates", "gold breakout", "dollar index", "equity breadth", "volatility regime"],
      "jelCodes": [],
      "pages": 24,
      "copyright": "© 2025 Saptanga Nupura Quant Research",
      "keyTakeaways": [],
      "image": "/assets/cover/SNQR-2025-001.png",
      "summary": {
        "pdf": "/assets/research/SNQR-2025-001/summary/index.pdf",
        "pptx": "/assets/research/SNQR-2025-001/summary/index.pptx"
      },
      "reader": { "type": "pdf", "src": "/assets/research/SNQR-2025-001/pdf/index.pdf" },
      "audio": { "src": "/assets/research/SNQR-2025-001/audio/index.mp3" },
      "url": "/research/paper.html?id=SNQR-2025-001",
      "hasArticles": false,
      "articlesCount": 0,
      "articleIds": []
    },
    {
      "id": "SNQR-2025-002",
      "title": "The Rupee at Record Lows: Market Microstructure Meets Policy Resolve",
      "deck": "",
      "division": "Arc of Markets Research",
      "format": "Research",
      "cat": "flagship",
      "publishDate": "2025-07-30",
      "editorsPick": true,
      "keywords": ["INR/USD", "RBI intervention", "FX liquidity", "carry trade", "sovereign flows"],
      "jelCodes": [],
      "pages": 24,
      "copyright": "© 2025 Saptanga Nupura Quant Research",
      "keyTakeaways": [],
      "image": "/assets/cover/SNQR-2025-002.png",
      "summary": {
        "pdf": "/assets/research/SNQR-2025-002/summary/index.pdf",
        "pptx": "/assets/research/SNQR-2025-002/summary/index.pptx"
      },
      "reader": { "type": "pdf", "src": "/assets/research/SNQR-2025-002/pdf/index.pdf" },
      "audio": { "src": "/assets/research/SNQR-2025-002/audio/index.mp3" },
      "url": "/research/paper.html?id=SNQR-2025-002",
      "hasArticles": false,
      "articlesCount": 0,
      "articleIds": []
    },
    {
      "id": "SNQR-2025-003",
      "title": "Oil’s Balancing Act: OPEC+ Signaling vs. Demand Softening",
      "deck": "",
      "division": "Arc of Markets Research",
      "format": "Research",
      "cat": "flagship",
      "publishDate": "2025-07-31",
      "editorsPick": true,
      "keywords": ["OPEC+", "supply discipline", "demand elasticity", "Brent curve", "refinery margins"],
      "jelCodes": [],
      "pages": 24,
      "copyright": "© 2025 Saptanga Nupura Quant Research",
      "keyTakeaways": [],
      "image": "/assets/cover/SNQR-2025-003.png",
      "summary": {
        "pdf": "/assets/research/SNQR-2025-003/summary/index.pdf",
        "pptx": "/assets/research/SNQR-2025-003/summary/index.pptx"
      },
      "reader": { "type": "pdf", "src": "/assets/research/SNQR-2025-003/pdf/index.pdf" },
      "audio": { "src": "/assets/research/SNQR-2025-003/audio/index.mp3" },
      "url": "/research/paper.html?id=SNQR-2025-003",
      "hasArticles": false,
      "articlesCount": 0,
      "articleIds": []
    },
    {
      "id": "SNQR-2025-004",
      "title": "Leverage & Hope in Shanghai: Can China’s Rally Survive the Credit Cycle?",
      "deck": "",
      "division": "Arc of Markets Research",
      "format": "Research",
      "cat": "flagship",
      "publishDate": "2025-08-01",
      "editorsPick": true,
      "keywords": ["margin financing", "CSI indices", "household flows", "property drag", "policy put"],
      "jelCodes": [],
      "pages": 24,
      "copyright": "© 2025 Saptanga Nupura Quant Research",
      "keyTakeaways": [],
      "image": "/assets/cover/SNQR-2025-004.png",
      "summary": {
        "pdf": "/assets/research/SNQR-2025-004/summary/index.pdf",
        "pptx": "/assets/research/SNQR-2025-004/summary/index.pptx"
      },
      "reader": { "type": "pdf", "src": "/assets/research/SNQR-2025-004/pdf/index.pdf" },
      "audio": { "src": "/assets/research/SNQR-2025-004/audio/index.mp3" },
      "url": "/research/paper.html?id=SNQR-2025-004",
      "hasArticles": false,
      "articlesCount": 0,
      "articleIds": []
    },
    {
      "id": "SNQR-2025-005",
      "title": "Tariffs as Monetary Shock: Re-Pricing India–US Ties Through the Macro Lens",
      "deck": "",
      "division": "Engines of State Research",
      "format": "Research",
      "cat": "flagship",
      "publishDate": "2025-08-04",
      "editorsPick": true,
      "keywords": ["trade policy", "imported inflation", "CAD", "growth impulse", "policy mix"],
      "jelCodes": [],
      "pages": 24,
      "copyright": "© 2025 Saptanga Nupura Quant Research",
      "keyTakeaways": [],
      "image": "/assets/cover/SNQR-2025-005.png",
      "summary": {
        "pdf": "/assets/research/SNQR-2025-005/summary/index.pdf",
        "pptx": "/assets/research/SNQR-2025-005/summary/index.pptx"
      },
      "reader": { "type": "pdf", "src": "/assets/research/SNQR-2025-005/pdf/index.pdf" },
      "audio": { "src": "/assets/research/SNQR-2025-005/audio/index.mp3" },
      "url": "/research/paper.html?id=SNQR-2025-005",
      "hasArticles": false,
      "articlesCount": 0,
      "articleIds": []
    },
    {
      "id": "SNQR-2025-006",
      "title": "The Central Bank Trilemma: Cutting Without Capitulating to Inflation",
      "deck": "",
      "division": "Engines of State Research",
      "format": "Research",
      "cat": "flagship",
      "publishDate": "2025-08-05",
      "editorsPick": true,
      "keywords": ["policy rate path", "output gap", "inflation expectations", "QT vs QE", "forward guidance"],
      "jelCodes": [],
      "pages": 24,
      "copyright": "© 2025 Saptanga Nupura Quant Research",
      "keyTakeaways": [],
      "image": "/assets/cover/SNQR-2025-006.png",
      "summary": {
        "pdf": "/assets/research/SNQR-2025-006/summary/index.pdf",
        "pptx": "/assets/research/SNQR-2025-006/summary/index.pptx"
      },
      "reader": { "type": "pdf", "src": "/assets/research/SNQR-2025-006/pdf/index.pdf" },
      "audio": { "src": "/assets/research/SNQR-2025-006/audio/index.mp3" },
      "url": "/research/paper.html?id=SNQR-2025-006",
      "hasArticles": false,
      "articlesCount": 0,
      "articleIds": []
    },
    {
      "id": "SNQR-2025-007",
      "title": "Fiscal Glidepaths Under Stress: Capex Ambition in a Higher-For-Longer World",
      "deck": "",
      "division": "Engines of State Research",
      "format": "Research",
      "cat": "flagship",
      "publishDate": "2025-08-06",
      "editorsPick": true,
      "keywords": ["fiscal deficit", "capex multiplier", "bond supply", "term premium", "crowding-out"],
      "jelCodes": [],
      "pages": 24,
      "copyright": "© 2025 Saptanga Nupura Quant Research",
      "keyTakeaways": [],
      "image": "/assets/cover/SNQR-2025-007.png",
      "summary": {
        "pdf": "/assets/research/SNQR-2025-007/summary/index.pdf",
        "pptx": "/assets/research/SNQR-2025-007/summary/index.pptx"
      },
      "reader": { "type": "pdf", "src": "/assets/research/SNQR-2025-007/pdf/index.pdf" },
      "audio": { "src": "/assets/research/SNQR-2025-007/audio/index.mp3" },
      "url": "/research/paper.html?id=SNQR-2025-007",
      "hasArticles": false,
      "articlesCount": 0,
      "articleIds": []
    },
    {
      "id": "SNQR-2025-008",
      "title": "Intervening Quietly: FX Defenses, Swap Lines, and the New Playbook",
      "deck": "",
      "division": "Engines of State Research",
      "format": "Research",
      "cat": "flagship",
      "publishDate": "2025-08-07",
      "editorsPick": true,
      "keywords": ["FX reserves", "sterilization", "NDF markets", "liquidity corridors", "balance of payments"],
      "jelCodes": [],
      "pages": 24,
      "copyright": "© 2025 Saptanga Nupura Quant Research",
      "keyTakeaways": [],
      "image": "/assets/cover/SNQR-2025-008.png",
      "summary": {
        "pdf": "/assets/research/SNQR-2025-008/summary/index.pdf",
        "pptx": "/assets/research/SNQR-2025-008/summary/index.pptx"
      },
      "reader": { "type": "pdf", "src": "/assets/research/SNQR-2025-008/pdf/index.pdf" },
      "audio": { "src": "/assets/research/SNQR-2025-008/audio/index.mp3" },
      "url": "/research/paper.html?id=SNQR-2025-008",
      "hasArticles": false,
      "articlesCount": 0,
      "articleIds": []
    },
    {
      "id": "SNQR-2025-009",
      "title": "Gaskets of the Global Order: EV Tariffs, Pork Duties, and the New Trade Chess",
      "deck": "",
      "division": "Diplomatic Frontiers Research",
      "format": "Research",
      "cat": "flagship",
      "publishDate": "2025-08-08",
      "editorsPick": true,
      "keywords": ["EU–China", "anti-dumping", "supply chains", "retaliation ladder", "rule-setting"],
      "jelCodes": [],
      "pages": 24,
      "copyright": "© 2025 Saptanga Nupura Quant Research",
      "keyTakeaways": [],
      "image": "/assets/cover/SNQR-2025-009.png",
      "summary": {
        "pdf": "/assets/research/SNQR-2025-009/summary/index.pdf",
        "pptx": "/assets/research/SNQR-2025-009/summary/index.pptx"
      },
      "reader": { "type": "pdf", "src": "/assets/research/SNQR-2025-009/pdf/index.pdf" },
      "audio": { "src": "/assets/research/SNQR-2025-009/audio/index.mp3" },
      "url": "/research/paper.html?id=SNQR-2025-009",
      "hasArticles": false,
      "articlesCount": 0,
      "articleIds": []
    },
    {
      "id": "SNQR-2025-010",
      "title": "Alaska to Taipei: Quiet Dialogues That Move Deterrence",
      "deck": "",
      "division": "Diplomatic Frontiers Research",
      "format": "Research",
      "cat": "flagship",
      "publishDate": "2025-08-11",
      "editorsPick": true,
      "keywords": ["Taiwan Strait", "backchannel diplomacy", "escalation ladder", "Indo-Pacific", "security guarantees"],
      "jelCodes": [],
      "pages": 24,
      "copyright": "© 2025 Saptanga Nupura Quant Research",
      "keyTakeaways": [],
      "image": "/assets/cover/SNQR-2025-010.png",
      "summary": {
        "pdf": "/assets/research/SNQR-2025-010/summary/index.pdf",
        "pptx": "/assets/research/SNQR-2025-010/summary/index.pptx"
      },
      "reader": { "type": "pdf", "src": "/assets/research/SNQR-2025-010/pdf/index.pdf" },
      "audio": { "src": "/assets/research/SNQR-2025-010/audio/index.mp3" },
      "url": "/research/paper.html?id=SNQR-2025-010",
      "hasArticles": false,
      "articlesCount": 0,
      "articleIds": []
    },
    {
      "id": "SNQR-2025-011",
      "title": "From Gaza to the Gulf: Energy, Diplomacy, and Fragile Equilibria",
      "deck": "",
      "division": "Diplomatic Frontiers Research",
      "format": "Research",
      "cat": "flagship",
      "publishDate": "2025-08-12",
      "editorsPick": true,
      "keywords": ["ceasefire diplomacy", "oil risk premium", "regional alliances", "maritime security", "humanitarian corridors"],
      "jelCodes": [],
      "pages": 24,
      "copyright": "© 2025 Saptanga Nupura Quant Research",
      "keyTakeaways": [],
      "image": "/assets/cover/SNQR-2025-011.png",
      "summary": {
        "pdf": "/assets/research/SNQR-2025-011/summary/index.pdf",
        "pptx": "/assets/research/SNQR-2025-011/summary/index.pptx"
      },
      "reader": { "type": "pdf", "src": "/assets/research/SNQR-2025-011/pdf/index.pdf" },
      "audio": { "src": "/assets/research/SNQR-2025-011/audio/index.mp3" },
      "url": "/research/paper.html?id=SNQR-2025-011",
      "hasArticles": false,
      "articlesCount": 0,
      "articleIds": []
    },
    {
      "id": "SNQR-2025-012",
      "title": "SCO, BRICS, and the Middle Corridor: Rerouting Influence Across Eurasia",
      "deck": "",
      "division": "Diplomatic Frontiers Research",
      "format": "Research",
      "cat": "flagship",
      "publishDate": "2025-08-13",
      "editorsPick": true,
      "keywords": ["regional blocs", "corridors", "sanctions evasion", "payment systems", "multipolarity"],
      "jelCodes": [],
      "pages": 24,
      "copyright": "© 2025 Saptanga Nupura Quant Research",
      "keyTakeaways": [],
      "image": "/assets/cover/SNQR-2025-012.png",
      "summary": {
        "pdf": "/assets/research/SNQR-2025-012/summary/index.pdf",
        "pptx": "/assets/research/SNQR-2025-012/summary/index.pptx"
      },
      "reader": { "type": "pdf", "src": "/assets/research/SNQR-2025-012/pdf/index.pdf" },
      "audio": { "src": "/assets/research/SNQR-2025-012/audio/index.mp3" },
      "url": "/research/paper.html?id=SNQR-2025-012",
      "hasArticles": false,
      "articlesCount": 0,
      "articleIds": []
    },

    {
      "id": "SNQR-2025-013",
      "title": "AI Supply Chains After TSMC: The New Geography of Compute Sovereignty",
      "deck": "",
      "division": "Futurecrafting Research",
      "format": "Research",
      "cat": "flagship",
      "publishDate": "2025-08-14",
      "editorsPick": true,
      "keywords": ["chip export controls", "foundry risk", "onshore capacity", "capex cycles", "techno-industrial policy"],
      "jelCodes": [],
      "pages": 24,
      "copyright": "© 2025 Saptanga Nupura Quant Research",
      "keyTakeaways": [],
      "image": "/assets/cover/SNQR-2025-013.png",
      "summary": {
        "pdf": "/assets/research/SNQR-2025-013/summary/index.pdf",
        "pptx": "/assets/research/SNQR-2025-013/summary/index.pptx"
      },
      "reader": { "type": "pdf", "src": "/assets/research/SNQR-2025-013/pdf/index.pdf" },
      "audio": { "src": "/assets/research/SNQR-2025-013/audio/index.mp3" },
      "url": "/research/paper.html?id=SNQR-2025-013",
      "hasArticles": false,
      "articlesCount": 0,
      "articleIds": []
    },
    {
      "id": "SNQR-2025-014",
      "title": "De-Risking vs. Decoupling: Industrial Policy When Politics Sets the Cost of Capital",
      "deck": "",
      "division": "Futurecrafting Research",
      "format": "Research",
      "cat": "flagship",
      "publishDate": "2025-08-15",
      "editorsPick": true,
      "keywords": ["subsidies", "CBAM/standards", "industrial strategy", "WACC", "strategic autonomy"],
      "jelCodes": [],
      "pages": 24,
      "copyright": "© 2025 Saptanga Nupura Quant Research",
      "keyTakeaways": [],
      "image": "/assets/cover/SNQR-2025-014.png",
      "summary": {
        "pdf": "/assets/research/SNQR-2025-014/summary/index.pdf",
        "pptx": "/assets/research/SNQR-2025-014/summary/index.pptx"
      },
      "reader": { "type": "pdf", "src": "/assets/research/SNQR-2025-014/pdf/index.pdf" },
      "audio": { "src": "/assets/research/SNQR-2025-014/audio/index.mp3" },
      "url": "/research/paper.html?id=SNQR-2025-014",
      "hasArticles": false,
      "articlesCount": 0,
      "articleIds": []
    },
    {
      "id": "SNQR-2025-015",
      "title": "The EV Tariff Wall: Who Wins the Affordable Electrification Race?",
      "deck": "",
      "division": "Futurecrafting Research",
      "format": "Research",
      "cat": "flagship",
      "publishDate": "2025-08-18",
      "editorsPick": true,
      "keywords": ["EV penetration", "cost curve", "battery supply", "tariff pass-through", "consumer surplus"],
      "jelCodes": [],
      "pages": 24,
      "copyright": "© 2025 Saptanga Nupura Quant Research",
      "keyTakeaways": [],
      "image": "/assets/cover/SNQR-2025-015.png",
      "summary": {
        "pdf": "/assets/research/SNQR-2025-015/summary/index.pdf",
        "pptx": "/assets/research/SNQR-2025-015/summary/index.pptx"
      },
      "reader": { "type": "pdf", "src": "/assets/research/SNQR-2025-015/pdf/index.pdf" },
      "audio": { "src": "/assets/research/SNQR-2025-015/audio/index.mp3" },
      "url": "/research/paper.html?id=SNQR-2025-015",
      "hasArticles": false,
      "articlesCount": 0,
      "articleIds": []
    },
    {
      "id": "SNQR-2025-016",
      "title": "Financial Infrastructure 2030: CBDCs, Tokenized Gilts, and Collateral Mobility",
      "deck": "",
      "division": "Futurecrafting Research",
      "format": "Research",
      "cat": "flagship",
      "publishDate": "2025-08-19",
      "editorsPick": true,
      "keywords": ["digital money", "tokenization", "repo markets", "settlement risk", "market plumbing"],
      "jelCodes": [],
      "pages": 24,
      "copyright": "© 2025 Saptanga Nupura Quant Research",
      "keyTakeaways": [],
      "image": "/assets/cover/SNQR-2025-016.png",
      "summary": {
        "pdf": "/assets/research/SNQR-2025-016/summary/index.pdf",
        "pptx": "/assets/research/SNQR-2025-016/summary/index.pptx"
      },
      "reader": { "type": "pdf", "src": "/assets/research/SNQR-2025-016/pdf/index.pdf" },
      "audio": { "src": "/assets/research/SNQR-2025-016/audio/index.mp3" },
      "url": "/research/paper.html?id=SNQR-2025-016",
      "hasArticles": false,
      "articlesCount": 0,
      "articleIds": []
    },

    {
      "id": "SNQR-2025-017",
      "title": "The Alliance Basis Trade: NATO, BRICS, and Capital’s Quiet Realignment",
      "deck": "",
      "division": "Clubs of Influence Research",
      "format": "Research",
      "cat": "signature",
      "publishDate": "2025-08-20",
      "editorsPick": true,
      "keywords": ["security blocs", "reserve flows", "defense capex", "sanctions architecture", "FX blocs"],
      "jelCodes": [],
      "pages": 24,
      "copyright": "© 2025 Saptanga Nupura Quant Research",
      "keyTakeaways": [],
      "image": "/assets/cover/SNQR-2025-017.png",
      "summary": {
        "pdf": "/assets/research/SNQR-2025-017/summary/index.pdf",
        "pptx": "/assets/research/SNQR-2025-017/summary/index.pptx"
      },
      "reader": { "type": "pdf", "src": "/assets/research/SNQR-2025-017/pdf/index.pdf" },
      "audio": { "src": "/assets/research/SNQR-2025-017/audio/index.mp3" },
      "url": "/research/paper.html?id=SNQR-2025-017",
      "hasArticles": false,
      "articlesCount": 0,
      "articleIds": []
    },
    {
      "id": "SNQR-2025-018",
      "title": "Tariffs as Alliance Signaling: Reading the Subtext of Trade Penalties",
      "deck": "",
      "division": "Clubs of Influence Research",
      "format": "Research",
      "cat": "signature",
      "publishDate": "2025-08-21",
      "editorsPick": true,
      "keywords": ["coercive economics", "tariff elasticity", "friend-shoring", "compliance risk", "dispute settlement"],
      "jelCodes": [],
      "pages": 24,
      "copyright": "© 2025 Saptanga Nupura Quant Research",
      "keyTakeaways": [],
      "image": "/assets/cover/SNQR-2025-018.png",
      "summary": {
        "pdf": "/assets/research/SNQR-2025-018/summary/index.pdf",
        "pptx": "/assets/research/SNQR-2025-018/summary/index.pptx"
      },
      "reader": { "type": "pdf", "src": "/assets/research/SNQR-2025-018/pdf/index.pdf" },
      "audio": { "src": "/assets/research/SNQR-2025-018/audio/index.mp3" },
      "url": "/research/paper.html?id=SNQR-2025-018",
      "hasArticles": false,
      "articlesCount": 0,
      "articleIds": []
    },
    {
      "id": "SNQR-2025-019",
      "title": "Arms, Apps, and Access: Techno-Security Pacts in a Fragmenting Internet",
      "deck": "",
      "division": "Clubs of Influence Research",
      "format": "Research",
      "cat": "signature",
      "publishDate": "2025-08-22",
      "editorsPick": true,
      "keywords": ["export controls", "data sovereignty", "5G/AI stacks", "standards war", "licensing regimes"],
      "jelCodes": [],
      "pages": 24,
      "copyright": "© 2025 Saptanga Nupura Quant Research",
      "keyTakeaways": [],
      "image": "/assets/cover/SNQR-2025-019.png",
      "summary": {
        "pdf": "/assets/research/SNQR-2025-019/summary/index.pdf",
        "pptx": "/assets/research/SNQR-2025-019/summary/index.pptx"
      },
      "reader": { "type": "pdf", "src": "/assets/research/SNQR-2025-019/pdf/index.pdf" },
      "audio": { "src": "/assets/research/SNQR-2025-019/audio/index.mp3" },
      "url": "/research/paper.html?id=SNQR-2025-019",
      "hasArticles": false,
      "articlesCount": 0,
      "articleIds": []
    },
    {
      "id": "SNQR-2025-020",
      "title": "G20 to “G-Who”? The Shrinking Commons and the Rise of Minilateral Deals",
      "deck": "",
      "division": "Clubs of Influence Research",
      "format": "Research",
      "cat": "signature",
      "publishDate": "2025-08-25",
      "editorsPick": true,
      "keywords": ["global governance", "minilateralism", "forum shopping", "policy spillovers", "agenda-setting"],
      "jelCodes": [],
      "pages": 24,
      "copyright": "© 2025 Saptanga Nupura Quant Research",
      "keyTakeaways": [],
      "image": "/assets/cover/SNQR-2025-020.png",
      "summary": {
        "pdf": "/assets/research/SNQR-2025-020/summary/index.pdf",
        "pptx": "/assets/research/SNQR-2025-020/summary/index.pptx"
      },
      "reader": { "type": "pdf", "src": "/assets/research/SNQR-2025-020/pdf/index.pdf" },
      "audio": { "src": "/assets/research/SNQR-2025-020/audio/index.mp3" },
      "url": "/research/paper.html?id=SNQR-2025-020",
      "hasArticles": false,
      "articlesCount": 0,
      "articleIds": []
    },

    {
      "id": "SNQR-2025-021",
      "title": "Petro-Pragmatism: OPEC+ Strategy at the Edge of Slowing Demand",
      "deck": "",
      "division": "Resource Geopolitics Research",
      "format": "Research",
      "cat": "signature",
      "publishDate": "2025-08-26",
      "editorsPick": true,
      "keywords": ["spare capacity", "quota compliance", "demand elasticity", "inventories", "backwardation"],
      "jelCodes": [],
      "pages": 24,
      "copyright": "© 2025 Saptanga Nupura Quant Research",
      "keyTakeaways": [],
      "image": "/assets/cover/SNQR-2025-021.png",
      "summary": {
        "pdf": "/assets/research/SNQR-2025-021/summary/index.pdf",
        "pptx": "/assets/research/SNQR-2025-021/summary/index.pptx"
      },
      "reader": { "type": "pdf", "src": "/assets/research/SNQR-2025-021/pdf/index.pdf" },
      "audio": { "src": "/assets/research/SNQR-2025-021/audio/index.mp3" },
      "url": "/research/paper.html?id=SNQR-2025-021",
      "hasArticles": false,
      "articlesCount": 0,
      "articleIds": []
    },
    {
      "id": "SNQR-2025-022",
      "title": "LNG and the New Map: Asia’s Bids, Europe’s Winters, and Price Floors",
      "deck": "",
      "division": "Resource Geopolitics Research",
      "format": "Research",
      "cat": "signature",
      "publishDate": "2025-08-27",
      "editorsPick": true,
      "keywords": ["LNG contracts", "spot vs term", "regas capacity", "TTF linkage", "energy security"],
      "jelCodes": [],
      "pages": 24,
      "copyright": "© 2025 Saptanga Nupura Quant Research",
      "keyTakeaways": [],
      "image": "/assets/cover/SNQR-2025-022.png",
      "summary": {
        "pdf": "/assets/research/SNQR-2025-022/summary/index.pdf",
        "pptx": "/assets/research/SNQR-2025-022/summary/index.pptx"
      },
      "reader": { "type": "pdf", "src": "/assets/research/SNQR-2025-022/pdf/index.pdf" },
      "audio": { "src": "/assets/research/SNQR-2025-022/audio/index.mp3" },
      "url": "/research/paper.html?id=SNQR-2025-022",
      "hasArticles": false,
      "articlesCount": 0,
      "articleIds": []
    },
    {
      "id": "SNQR-2025-023",
      "title": "Minerals of Power: Nickel, Copper, and the Politics of Refining",
      "deck": "",
      "division": "Resource Geopolitics Research",
      "format": "Research",
      "cat": "signature",
      "publishDate": "2025-08-28",
      "editorsPick": true,
      "keywords": ["critical minerals", "refining concentration", "ESG constraints", "offtake agreements", "resource nationalism"],
      "jelCodes": [],
      "pages": 24,
      "copyright": "© 2025 Saptanga Nupura Quant Research",
      "keyTakeaways": [],
      "image": "/assets/cover/SNQR-2025-023.png",
      "summary": {
        "pdf": "/assets/research/SNQR-2025-023/summary/index.pdf",
        "pptx": "/assets/research/SNQR-2025-023/summary/index.pptx"
      },
      "reader": { "type": "pdf", "src": "/assets/research/SNQR-2025-023/pdf/index.pdf" },
      "audio": { "src": "/assets/research/SNQR-2025-023/audio/index.mp3" },
      "url": "/research/paper.html?id=SNQR-2025-023",
      "hasArticles": false,
      "articlesCount": 0,
      "articleIds": []
    },
    {
      "id": "SNQR-2025-024",
      "title": "Maritime Choke Points: Freight, Risk Premiums, and Insurance in Conflict Zones",
      "deck": "",
      "division": "Resource Geopolitics Research",
      "format": "Research",
      "cat": "signature",
      "publishDate": "2025-08-29",
      "editorsPick": true,
      "keywords": ["shipping lanes", "war risk", "freight rates", "marine insurance", "supply resilience"],
      "jelCodes": [],
      "pages": 24,
      "copyright": "© 2025 Saptanga Nupura Quant Research",
      "keyTakeaways": [],
      "image": "/assets/cover/SNQR-2025-024.png",
      "summary": {
        "pdf": "/assets/research/SNQR-2025-024/summary/index.pdf",
        "pptx": "/assets/research/SNQR-2025-024/summary/index.pptx"
      },
      "reader": { "type": "pdf", "src": "/assets/research/SNQR-2025-024/pdf/index.pdf" },
      "audio": { "src": "/assets/research/SNQR-2025-024/audio/index.mp3" },
      "url": "/research/paper.html?id=SNQR-2025-024",
      "hasArticles": false,
      "articlesCount": 0,
      "articleIds": []
    },

    {
      "id": "SNQR-2025-025",
      "title": "Carbon as Collateral: Can Sovereigns Monetize Emissions Reductions?",
      "deck": "",
      "division": "The Carbon & climatic Market Ledger Research",
      "format": "Research",
      "cat": "signature",
      "publishDate": "2025-09-01",
      "editorsPick": true,
      "keywords": ["carbon markets", "climate finance", "Article 6", "blended finance", "sovereign risk"],
      "jelCodes": [],
      "pages": 24,
      "copyright": "© 2025 Saptanga Nupura Quant Research",
      "keyTakeaways": [],
      "image": "/assets/cover/SNQR-2025-025.png",
      "summary": {
        "pdf": "/assets/research/SNQR-2025-025/summary/index.pdf",
        "pptx": "/assets/research/SNQR-2025-025/summary/index.pptx"
      },
      "reader": { "type": "pdf", "src": "/assets/research/SNQR-2025-025/pdf/index.pdf" },
      "audio": { "src": "/assets/research/SNQR-2025-025/audio/index.mp3" },
      "url": "/research/paper.html?id=SNQR-2025-025",
      "hasArticles": false,
      "articlesCount": 0,
      "articleIds": []
    },
    {
      "id": "SNQR-2025-026",
      "title": "Monsoons, Food Inflation, and the Macro-Climate Nexus",
      "deck": "",
      "division": "The Carbon & climatic Market Ledger Research",
      "format": "Research",
      "cat": "signature",
      "publishDate": "2025-09-02",
      "editorsPick": true,
      "keywords": ["agri supply shocks", "CPI food", "weather risk", "crop yields", "buffer stocks"],
      "jelCodes": [],
      "pages": 24,
      "copyright": "© 2025 Saptanga Nupura Quant Research",
      "keyTakeaways": [],
      "image": "/assets/cover/SNQR-2025-026.png",
      "summary": {
        "pdf": "/assets/research/SNQR-2025-026/summary/index.pdf",
        "pptx": "/assets/research/SNQR-2025-026/summary/index.pptx"
      },
      "reader": { "type": "pdf", "src": "/assets/research/SNQR-2025-026/pdf/index.pdf" },
      "audio": { "src": "/assets/research/SNQR-2025-026/audio/index.mp3" },
      "url": "/research/paper.html?id=SNQR-2025-026",
      "hasArticles": false,
      "articlesCount": 0,
      "articleIds": []
    },
    {
      "id": "SNQR-2025-027",
      "title": "Green Gilt or Greenwash? Pricing Transition Risk in Sovereign Debt",
      "deck": "",
      "division": "The Carbon & climatic Market Ledger Research",
      "format": "Research",
      "cat": "signature",
      "publishDate": "2025-09-03",
      "editorsPick": true,
      "keywords": ["green bonds", "transition pathways", "climate risk premium", "disclosure", "taxonomy"],
      "jelCodes": [],
      "pages": 24,
      "copyright": "© 2025 Saptanga Nupura Quant Research",
      "keyTakeaways": [],
      "image": "/assets/cover/SNQR-2025-027.png",
      "summary": {
        "pdf": "/assets/research/SNQR-2025-027/summary/index.pdf",
        "pptx": "/assets/research/SNQR-2025-027/summary/index.pptx"
      },
      "reader": { "type": "pdf", "src": "/assets/research/SNQR-2025-027/pdf/index.pdf" },
      "audio": { "src": "/assets/research/SNQR-2025-027/audio/index.mp3" },
      "url": "/research/paper.html?id=SNQR-2025-027",
      "hasArticles": false,
      "articlesCount": 0,
      "articleIds": []
    },
    {
      "id": "SNQR-2025-028",
      "title": "Steel, Cement, CBAM: Who Pays for the Planet’s Hard-to-Abate Sectors?",
      "deck": "",
      "division": "The Carbon & climatic Market Ledger Research",
      "format": "Research",
      "cat": "signature",
      "publishDate": "2025-09-04",
      "editorsPick": true,
      "keywords": ["border adjustment", "industrial emissions", "cost pass-through", "trade leakage", "competitiveness"],
      "jelCodes": [],
      "pages": 24,
      "copyright": "© 2025 Saptanga Nupura Quant Research",
      "keyTakeaways": [],
      "image": "/assets/cover/SNQR-2025-028.png",
      "summary": {
        "pdf": "/assets/research/SNQR-2025-028/summary/index.pdf",
        "pptx": "/assets/research/SNQR-2025-028/summary/index.pptx"
      },
      "reader": { "type": "pdf", "src": "/assets/research/SNQR-2025-028/pdf/index.pdf" },
      "audio": { "src": "/assets/research/SNQR-2025-028/audio/index.mp3" },
      "url": "/research/paper.html?id=SNQR-2025-028",
      "hasArticles": false,
      "articlesCount": 0,
      "articleIds": []
    },

    {
      "id": "SNQR-2025-029",
      "title": "The Post-GPU World? Custom Silicon, Broadcom’s Play, and the Next Compute S-Curve",
      "deck": "",
      "division": "Industria Nova Research",
      "format": "Research",
      "cat": "signature",
      "publishDate": "2025-09-05",
      "editorsPick": true,
      "keywords": ["AI accelerators", "ASIC vs GPU", "capex intensity", "hyperscaler spend", "vendor concentration"],
      "jelCodes": [],
      "pages": 24,
      "copyright": "© 2025 Saptanga Nupura Quant Research",
      "keyTakeaways": [],
      "image": "/assets/cover/SNQR-2025-029.png",
      "summary": {
        "pdf": "/assets/research/SNQR-2025-029/summary/index.pdf",
        "pptx": "/assets/research/SNQR-2025-029/summary/index.pptx"
      },
      "reader": { "type": "pdf", "src": "/assets/research/SNQR-2025-029/pdf/index.pdf" },
      "audio": { "src": "/assets/research/SNQR-2025-029/audio/index.mp3" },
      "url": "/research/paper.html?id=SNQR-2025-029",
      "hasArticles": false,
      "articlesCount": 0,
      "articleIds": []
    },
    {
      "id": "SNQR-2025-030",
      "title": "Chip Rules, Real Economies: Export Curbs and the Re-Routing of Moore’s Law",
      "deck": "",
      "division": "Industria Nova Research",
      "format": "Research",
      "cat": "signature",
      "publishDate": "2025-09-08",
      "editorsPick": true,
      "keywords": ["tech controls", "supply chain rewire", "equipment licensing", "yield risk", "semiconductor geopolitics"],
      "jelCodes": [],
      "pages": 24,
      "copyright": "© 2025 Saptanga Nupura Quant Research",
      "keyTakeaways": [],
      "image": "/assets/cover/SNQR-2025-030.png",
      "summary": {
        "pdf": "/assets/research/SNQR-2025-030/summary/index.pdf",
        "pptx": "/assets/research/SNQR-2025-030/summary/index.pptx"
      },
      "reader": { "type": "pdf", "src": "/assets/research/SNQR-2025-030/pdf/index.pdf" },
      "audio": { "src": "/assets/research/SNQR-2025-030/audio/index.mp3" },
      "url": "/research/paper.html?id=SNQR-2025-030",
      "hasArticles": false,
      "articlesCount": 0,
      "articleIds": []
    },
    {
      "id": "SNQR-2025-031",
      "title": "Defense Tech Goes Mainstream: Drones, EW, and the Market Value of Deterrence",
      "deck": "",
      "division": "Industria Nova Research",
      "format": "Research",
      "cat": "signature",
      "publishDate": "2025-09-09",
      "editorsPick": true,
      "keywords": ["ISR", "electronic warfare", "dual-use tech", "procurement cycles", "defense multiples"],
      "jelCodes": [],
      "pages": 24,
      "copyright": "© 2025 Saptanga Nupura Quant Research",
      "keyTakeaways": [],
      "image": "/assets/cover/SNQR-2025-031.png",
      "summary": {
        "pdf": "/assets/research/SNQR-2025-031/summary/index.pdf",
        "pptx": "/assets/research/SNQR-2025-031/summary/index.pptx"
      },
      "reader": { "type": "pdf", "src": "/assets/research/SNQR-2025-031/pdf/index.pdf" },
      "audio": { "src": "/assets/research/SNQR-2025-031/audio/index.mp3" },
      "url": "/research/paper.html?id=SNQR-2025-031",
      "hasArticles": false,
      "articlesCount": 0,
      "articleIds": []
    },
    {
      "id": "SNQR-2025-032",
      "title": "Pharma’s Quiet Arms Race: mRNA, AI-Discovery, and Patent Cliffs",
      "deck": "",
      "division": "Industria Nova Research",
      "format": "Research",
      "cat": "signature",
      "publishDate": "2025-09-10",
      "editorsPick": true,
      "keywords": ["biotech pipelines", "platform trials", "AI drug discovery", "IP expiries", "regulatory pathways"],
      "jelCodes": [],
      "pages": 24,
      "copyright": "© 2025 Saptanga Nupura Quant Research",
      "keyTakeaways": [],
      "image": "/assets/cover/SNQR-2025-032.png",
      "summary": {
        "pdf": "/assets/research/SNQR-2025-032/summary/index.pdf",
        "pptx": "/assets/research/SNQR-2025-032/summary/index.pptx"
      },
      "reader": { "type": "pdf", "src": "/assets/research/SNQR-2025-032/pdf/index.pdf" },
      "audio": { "src": "/assets/research/SNQR-2025-032/audio/index.mp3" },
      "url": "/research/paper.html?id=SNQR-2025-032",
      "hasArticles": false,
      "articlesCount": 0,
      "articleIds": []
    },

    {
      "id": "SNQR-2025-033",
      "title": "QAOA for Allocation: Quantum-Classical Hybrids Under Tariff and Rate Shocks",
      "deck": "",
      "division": "Quantum Horizons Research",
      "format": "Research",
      "cat": "lab",
      "publishDate": "2025-09-11",
      "editorsPick": true,
      "keywords": ["QAOA", "portfolio optimization", "regime shifts", "constraint sets", "hybrid solvers"],
      "jelCodes": [],
      "pages": 24,
      "copyright": "© 2025 Saptanga Nupura Quant Research",
      "keyTakeaways": [],
      "image": "/assets/cover/SNQR-2025-033.png",
      "summary": {
        "pdf": "/assets/research/SNQR-2025-033/summary/index.pdf",
        "pptx": "/assets/research/SNQR-2025-033/summary/index.pptx"
      },
      "reader": { "type": "pdf", "src": "/assets/research/SNQR-2025-033/pdf/index.pdf" },
      "audio": { "src": "/assets/research/SNQR-2025-033/audio/index.mp3" },
      "url": "/research/paper.html?id=SNQR-2025-033",
      "hasArticles": false,
      "articlesCount": 0,
      "articleIds": []
    },
    {
      "id": "SNQR-2025-034",
      "title": "Quantum Monte Carlo for Term Structure: Pricing Bonds in a Policy-Vol World",
      "deck": "",
      "division": "Quantum Horizons Research",
      "format": "Research",
      "cat": "lab",
      "publishDate": "2025-09-12",
      "editersPick": true,
      "keywords": ["QMC", "interest rate models", "path integrals", "convexity", "duration risk"],
      "jelCodes": [],
      "pages": 24,
      "copyright": "© 2025 Saptanga Nupura Quant Research",
      "keyTakeaways": [],
      "image": "/assets/cover/SNQR-2025-034.png",
      "summary": {
        "pdf": "/assets/research/SNQR-2025-034/summary/index.pdf",
        "pptx": "/assets/research/SNQR-2025-034/summary/index.pptx"
      },
      "reader": { "type": "pdf", "src": "/assets/research/SNQR-2025-034/pdf/index.pdf" },
      "audio": { "src": "/assets/research/SNQR-2025-034/audio/index.mp3" },
      "url": "/research/paper.html?id=SNQR-2025-034",
      "hasArticles": false,
      "articlesCount": 0,
      "articleIds": []
    },
    {
      "id": "SNQR-2025-035",
      "title": "Entangling Signals: Quantum Feature Maps for Macro Nowcasting",
      "deck": "",
      "division": "Quantum Horizons Research",
      "format": "Research",
      "cat": "lab",
      "publishDate": "2025-09-15",
      "editorsPick": true,
      "keywords": ["quantum kernels", "feature maps", "nowcasting", "dimensionality", "generalization"],
      "jelCodes": [],
      "pages": 24,
      "copyright": "© 2025 Saptanga Nupura Quant Research",
      "keyTakeaways": [],
      "image": "/assets/cover/SNQR-2025-035.png",
      "summary": {
        "pdf": "/assets/research/SNQR-2025-035/summary/index.pdf",
        "pptx": "/assets/research/SNQR-2025-035/summary/index.pptx"
      },
      "reader": { "type": "pdf", "src": "/assets/research/SNQR-2025-035/pdf/index.pdf" },
      "audio": { "src": "/assets/research/SNQR-2025-035/audio/index.mp3" },
      "url": "/research/paper.html?id=SNQR-2025-035",
      "hasArticles": false,
      "articlesCount": 0,
      "articleIds": []
    },
    {
      "id": "SNQR-2025-036",
      "title": "Option Smiles in Superposition: A Quantum Take on Vol-of-Vol",
      "deck": "",
      "division": "Quantum Horizons Research",
      "format": "Research",
      "cat": "lab",
      "publishDate": "2025-09-16",
      "editorsPick": true,
      "keywords": ["implied volatility", "vol surface", "stochastic vol", "quantum circuits", "calibration"],
      "jelCodes": [],
      "pages": 24,
      "copyright": "© 2025 Saptanga Nupura Quant Research",
      "keyTakeaways": [],
      "image": "/assets/cover/SNQR-2025-036.png",
      "summary": {
        "pdf": "/assets/research/SNQR-2025-036/summary/index.pdf",
        "pptx": "/assets/research/SNQR-2025-036/summary/index.pptx"
      },
      "reader": { "type": "pdf", "src": "/assets/research/SNQR-2025-036/pdf/index.pdf" },
      "audio": { "src": "/assets/research/SNQR-2025-036/audio/index.mp3" },
      "url": "/research/paper.html?id=SNQR-2025-036",
      "hasArticles": false,
      "articlesCount": 0,
      "articleIds": []
    },

    {
      "id": "SNQR-2025-037",
      "title": "Regime Radar: Bayesian Switching Models for the September Effect",
      "deck": "",
      "division": "Statistical Arsenal Research",
      "format": "Research",
      "cat": "lab",
      "publishDate": "2025-09-17",
      "editorsPick": true,
      "keywords": ["Markov switching", "market seasonality", "posterior inference", "drawdown control", "Sharpe stability"],
      "jelCodes": [],
      "pages": 24,
      "copyright": "© 2025 Saptanga Nupura Quant Research",
      "keyTakeaways": [],
      "image": "/assets/cover/SNQR-2025-037.png",
      "summary": {
        "pdf": "/assets/research/SNQR-2025-037/summary/index.pdf",
        "pptx": "/assets/research/SNQR-2025-037/summary/index.pptx"
      },
      "reader": { "type": "pdf", "src": "/assets/research/SNQR-2025-037/pdf/index.pdf" },
      "audio": { "src": "/assets/research/SNQR-2025-037/audio/index.mp3" },
      "url": "/research/paper.html?id=SNQR-2025-037",
      "hasArticles": false,
      "articlesCount": 0,
      "articleIds": []
    },
    {
      "id": "SNQR-2025-038",
      "title": "Durability of the AI Trade: Factor Decomposition Beyond Momentum",
      "deck": "",
      "division": "Statistical Arsenal Research",
      "format": "Research",
      "cat": "lab",
      "publishDate": "2025-09-18",
      "editorsPick": true,
      "keywords": ["factor models", "crowding", "residual returns", "microstructure bias", "risk budgeting"],
      "jelCodes": [],
      "pages": 24,
      "copyright": "© 2025 Saptanga Nupura Quant Research",
      "keyTakeaways": [],
      "image": "/assets/cover/SNQR-2025-038.png",
      "summary": {
        "pdf": "/assets/research/SNQR-2025-038/summary/index.pdf",
        "pptx": "/assets/research/SNQR-2025-038/summary/index.pptx"
      },
      "reader": { "type": "pdf", "src": "/assets/research/SNQR-2025-038/pdf/index.pdf" },
      "audio": { "src": "/assets/research/SNQR-2025-038/audio/index.mp3" },
      "url": "/research/paper.html?id=SNQR-2025-038",
      "hasArticles": false,
      "articlesCount": 0,
      "articleIds": []
    },
    {
      "id": "SNQR-2025-039",
      "title": "Tariff Shocks as Instruments: Causal Paths from Policy to Prices",
      "deck": "",
      "division": "Statistical Arsenal Research",
      "format": "Research",
      "cat": "lab",
      "publishDate": "2025-09-19",
      "editorsPick": true,
      "keywords": ["instrumental variables", "identification", "pass-through", "event studies", "treatment effects"],
      "jelCodes": [],
      "pages": 24,
      "copyright": "© 2025 Saptanga Nupura Quant Research",
      "keyTakeaways": [],
      "image": "/assets/cover/SNQR-2025-039.png",
      "summary": {
        "pdf": "/assets/research/SNQR-2025-039/summary/index.pdf",
        "pptx": "/assets/research/SNQR-2025-039/summary/index.pptx"
      },
      "reader": { "type": "pdf", "src": "/assets/research/SNQR-2025-039/pdf/index.pdf" },
      "audio": { "src": "/assets/research/SNQR-2025-039/audio/index.mp3" },
      "url": "/research/paper.html?id=SNQR-2025-039",
      "hasArticles": false,
      "articlesCount": 0,
      "articleIds": []
    },
    {
      "id": "SNQR-2025-040",
      "title": "The Gold Standard: Testing Safe-Haven Properties Across Cycles",
      "deck": "",
      "division": "Statistical Arsenal Research",
      "format": "Research",
      "cat": "lab",
      "publishDate": "2025-09-22",
      "editorsPick": true,
      "keywords": ["copulas", "tail dependence", "flight-to-quality", "correlation regimes", "stress testing"],
      "jelCodes": [],
      "pages": 24,
      "copyright": "© 2025 Saptanga Nupura Quant Research",
      "keyTakeaways": [],
      "image": "/assets/cover/SNQR-2025-040.png",
      "summary": {
        "pdf": "/assets/research/SNQR-2025-040/summary/index.pdf",
        "pptx": "/assets/research/SNQR-2025-040/summary/index.pptx"
      },
      "reader": { "type": "pdf", "src": "/assets/research/SNQR-2025-040/pdf/index.pdf" },
      "audio": { "src": "/assets/research/SNQR-2025-040/audio/index.mp3" },
      "url": "/research/paper.html?id=SNQR-2025-040",
      "hasArticles": false,
      "articlesCount": 0,
      "articleIds": []
    },

    {
      "id": "SNQR-2025-041",
      "title": "Liquidity Scarcity & the DII Bid: How India’s Tape Absorbed FII Selling",
      "deck": "",
      "division": "Market Resonance Research",
      "format": "Research",
      "cat": "lab",
      "publishDate": "2025-09-23",
      "editorsPick": true,
      "keywords": ["order-book depth", "net flows", "impact cost", "VWAP slippage", "market resilience"],
      "jelCodes": [],
      "pages": 24,
      "copyright": "© 2025 Saptanga Nupura Quant Research",
      "keyTakeaways": [],
      "image": "/assets/cover/SNQR-2025-041.png",
      "summary": {
        "pdf": "/assets/research/SNQR-2025-041/summary/index.pdf",
        "pptx": "/assets/research/SNQR-2025-041/summary/index.pptx"
      },
      "reader": { "type": "pdf", "src": "/assets/research/SNQR-2025-041/pdf/index.pdf" },
      "audio": { "src": "/assets/research/SNQR-2025-041/audio/index.mp3" },
      "url": "/research/paper.html?id=SNQR-2025-041",
      "hasArticles": false,
      "articlesCount": 0,
      "articleIds": []
    },
    {
      "id": "SNQR-2025-042",
      "title": "Gamma Fences: Options Positioning That Pins Indices on Key Dates",
      "deck": "",
      "division": "Market Resonance Research",
      "format": "Research",
      "cat": "lab",
      "publishDate": "2025-09-24",
      "editorsPick": true,
      "keywords": ["dealer gamma", "charm/flow", "strike congestion", "expiry dynamics", "hedging feedbacks"],
      "jelCodes": [],
      "pages": 24,
      "copyright": "© 2025 Saptanga Nupura Quant Research",
      "keyTakeaways": [],
      "image": "/assets/cover/SNQR-2025-042.png",
      "summary": {
        "pdf": "/assets/research/SNQR-2025-042/summary/index.pdf",
        "pptx": "/assets/research/SNQR-2025-042/summary/index.pptx"
      },
      "reader": { "type": "pdf", "src": "/assets/research/SNQR-2025-042/pdf/index.pdf" },
      "audio": { "src": "/assets/research/SNQR-2025-042/audio/index.mp3" },
      "url": "/research/paper.html?id=SNQR-2025-042",
      "hasArticles": false,
      "articlesCount": 0,
      "articleIds": []
    },
    {
      "id": "SNQR-2025-043",
      "title": "FX Orderbooks at the Edge: INR Microstructure During Record Lows",
      "deck": "",
      "division": "Market Resonance Research",
      "format": "Research",
      "cat": "lab",
      "publishDate": "2025-09-25",
      "editorsPick": true,
      "keywords": ["top-of-book", "NDF vs onshore", "sweep-to-fill", "latency", "intervention footprint"],
      "jelCodes": [],
      "pages": 24,
      "copyright": "© 2025 Saptanga Nupura Quant Research",
      "keyTakeaways": [],
      "image": "/assets/cover/SNQR-2025-043.png",
      "summary": {
        "pdf": "/assets/research/SNQR-2025-043/summary/index.pdf",
        "pptx": "/assets/research/SNQR-2025-043/summary/index.pptx"
      },
      "reader": { "type": "pdf", "src": "/assets/research/SNQR-2025-043/pdf/index.pdf" },
      "audio": { "src": "/assets/research/SNQR-2025-043/audio/index.mp3" },
      "url": "/research/paper.html?id=SNQR-2025-043",
      "hasArticles": false,
      "articlesCount": 0,
      "articleIds": []
    },
    {
      "id": "SNQR-2025-044",
      "title": "OPEC Announcements and Energy E-Mini Reflexivity",
      "deck": "",
      "division": "Market Resonance Research",
      "format": "Research",
      "cat": "lab",
      "publishDate": "2025-09-26",
      "editorsPick": true,
      "keywords": ["news shocks", "event windows", "price discovery", "futures microstructure", "spillovers"],
      "jelCodes": [],
      "pages": 24,
      "copyright": "© 2025 Saptanga Nupura Quant Research",
      "keyTakeaways": [],
      "image": "/assets/cover/SNQR-2025-044.png",
      "summary": {
        "pdf": "/assets/research/SNQR-2025-044/summary/index.pdf",
        "pptx": "/assets/research/SNQR-2025-044/summary/index.pptx"
      },
      "reader": { "type": "pdf", "src": "/assets/research/SNQR-2025-044/pdf/index.pdf" },
      "audio": { "src": "/assets/research/SNQR-2025-044/audio/index.mp3" },
      "url": "/research/paper.html?id=SNQR-2025-044",
      "hasArticles": false,
      "articlesCount": 0,
      "articleIds": []
    },

    {
      "id": "SNQR-2025-045",
      "title": "The Tariff Graph: Building a Knowledge Graph of Trade Actions and Asset Moves",
      "deck": "",
      "division": "Signal Architecture Research",
      "format": "Research",
      "cat": "lab",
      "publishDate": "2025-09-29",
      "editorsPick": true,
      "keywords": ["graph databases", "entity resolution", "event embeddings", "transmission channels", "cross-asset links"],
      "jelCodes": [],
      "pages": 24,
      "copyright": "© 2025 Saptanga Nupura Quant Research",
      "keyTakeaways": [],
      "image": "/assets/cover/SNQR-2025-045.png",
      "summary": {
        "pdf": "/assets/research/SNQR-2025-045/summary/index.pdf",
        "pptx": "/assets/research/SNQR-2025-045/summary/index.pptx"
      },
      "reader": { "type": "pdf", "src": "/assets/research/SNQR-2025-045/pdf/index.pdf" },
      "audio": { "src": "/assets/research/SNQR-2025-045/audio/index.mp3" },
      "url": "/research/paper.html?id=SNQR-2025-045",
      "hasArticles": false,
      "articlesCount": 0,
      "articleIds": []
    },
    {
      "id": "SNQR-2025-046",
      "title": "Central Bank Language Models: From Speeches to Rates with Fine-Tuned NLP",
      "deck": "",
      "division": "Signal Architecture Research",
      "format": "Research",
      "cat": "lab",
      "publishDate": "2025-09-30",
      "editorsPick": true,
      "keywords": ["speech embeddings", "sentiment", "policy path", "textual factors", "forward rates"],
      "jelCodes": [],
      "pages": 24,
      "copyright": "© 2025 Saptanga Nupura Quant Research",
      "keyTakeaways": [],
      "image": "/assets/cover/SNQR-2025-046.png",
      "summary": {
        "pdf": "/assets/research/SNQR-2025-046/summary/index.pdf",
        "pptx": "/assets/research/SNQR-2025-046/summary/index.pptx"
      },
      "reader": { "type": "pdf", "src": "/assets/research/SNQR-2025-046/pdf/index.pdf" },
      "audio": { "src": "/assets/research/SNQR-2025-046/audio/index.mp3" },
      "url": "/research/paper.html?id=SNQR-2025-046",
      "hasArticles": false,
      "articlesCount": 0,
      "articleIds": []
    },
    {
      "id": "SNQR-2025-047",
      "title": "AIS to Alpha: Shipping Telemetry as a Nowcast for Global Demand",
      "deck": "",
      "division": "Signal Architecture Research",
      "format": "Research",
      "cat": "lab",
      "publishDate": "2025-10-01",
      "editorsPick": true,
      "keywords": ["AIS data", "port congestion", "supply chains", "demand proxies", "predictive signals"],
      "jelCodes": [],
      "pages": 24,
      "copyright": "© 2025 Saptanga Nupura Quant Research",
      "keyTakeaways": [],
      "image": "/assets/cover/SNQR-2025-047.png",
      "summary": {
        "pdf": "/assets/research/SNQR-2025-047/summary/index.pdf",
        "pptx": "/assets/research/SNQR-2025-047/summary/index.pptx"
      },
      "reader": { "type": "pdf", "src": "/assets/research/SNQR-2025-047/pdf/index.pdf" },
      "audio": { "src": "/assets/research/SNQR-2025-047/audio/index.mp3" },
      "url": "/research/paper.html?id=SNQR-2025-047",
      "hasArticles": false,
      "articlesCount": 0,
      "articleIds": []
    },
    {
      "id": "SNQR-2025-048",
      "title": "War-Wire: Real-Time Conflict Feeds and Portfolio Defense",
      "deck": "",
      "division": "Signal Architecture Research",
      "format": "Research",
      "cat": "lab",
      "publishDate": "2025-10-02",
      "editorsPick": true,
      "keywords": ["alt-data fusion", "geospatial", "anomaly detection", "risk overlays", "hedging triggers"],
      "jelCodes": [],
      "pages": 24,
      "copyright": "© 2025 Saptanga Nupura Quant Research",
      "keyTakeaways": [],
      "image": "/assets/cover/SNQR-2025-048.png",
      "summary": {
        "pdf": "/assets/research/SNQR-2025-048/summary/index.pdf",
        "pptx": "/assets/research/SNQR-2025-048/summary/index.pptx"
      },
      "reader": { "type": "pdf", "src": "/assets/research/SNQR-2025-048/pdf/index.pdf" },
      "audio": { "src": "/assets/research/SNQR-2025-048/audio/index.mp3" },
      "url": "/research/paper.html?id=SNQR-2025-048",
      "hasArticles": false,
      "articlesCount": 0,
      "articleIds": []
    }
  ]
}

